nikoperations/__init__.py
nikoperations/addition.py
nikoperations/subtraction.py
nikoperations-0.1.dist-info/METADATA
nikoperations-0.1.dist-info/WHEEL
nikoperations-0.1.dist-info/top_level.txt
nikoperations-0.1.dist-info/RECORD
