Metadata-Version: 2.1
Name: nikoperations
Version: 0.1
Summary: Basic math operations module
Home-page: https://github.com/Nikhil18Patil/nikoperations.git
Author: Nikhil Patil
Author-email: nikhilpatil18012004@gmail.com
